scikit_mtr/__init__.py
scikit_mtr/multi_output_framework.py
scikit_mtr/multi_output_stacking.py
scikit_mtr/multi_output_tools.py
scikit_mtr/setup.py
scikit_MTR-0.1.0.dist-info/METADATA
scikit_MTR-0.1.0.dist-info/WHEEL
scikit_MTR-0.1.0.dist-info/top_level.txt
scikit_MTR-0.1.0.dist-info/RECORD
