Metadata-Version: 2.1
Name: scikit-MTR
Version: 0.1.0
Summary: A sklearn-compatible framework for multi-task regression in Python.
Home-page: https://github.com/hengzhe-zhang/Scikit-MTR
Author: Hengzhe Zhang
Author-email: 
Classifier: Development Status :: 3 - Alpha
Classifier: Intended Audience :: Developers
Classifier: Intended Audience :: Science/Research
Classifier: Topic :: Software Development :: Libraries :: Python Modules
Classifier: Topic :: Scientific/Engineering :: Artificial Intelligence
Classifier: License :: OSI Approved :: MIT License
Classifier: Programming Language :: Python :: 3
Classifier: Programming Language :: Python :: 3.6
Classifier: Programming Language :: Python :: 3.7
Classifier: Programming Language :: Python :: 3.8
Classifier: Programming Language :: Python :: 3.9
Requires-Python: >=3.6
Requires-Dist: numpy
Requires-Dist: scikit-learn
